lspreader/__init__.py
lspreader/dotlsp.py
lspreader/flds.py
lspreader/lspreader.py
lspreader/misc.py
lspreader/nearest.py
lspreader/p4writer.py
lspreader/pext.py
lspreader/pmovie.py
lspreader-0.1.8.data/scripts/filter-pext.py
lspreader-0.1.8.data/scripts/p4header.py
lspreader-0.1.8.data/scripts/p4read.py
lspreader-0.1.8.data/scripts/simple-pext.py
lspreader-0.1.8.data/scripts/split-pext.py
lspreader-0.1.8.dist-info/LICENSE.md
lspreader-0.1.8.dist-info/METADATA
lspreader-0.1.8.dist-info/WHEEL
lspreader-0.1.8.dist-info/top_level.txt
lspreader-0.1.8.dist-info/RECORD
