Metadata-Version: 2.1
Name: lspreader
Version: 0.1.8
Summary: A set of python readers for the code LSP
Home-page: http://github.com/noobermin/lspreader
Author: noobermin
Author-email: ngirmang.1@osu.com
License: MIT
Platform: UNKNOWN
Requires-Dist: numpy (>=1.13.1)
Requires-Dist: scipy (>=0.19.1)
Requires-Dist: pys (>=0.0.14)
Requires-Dist: docopt (>=0.6.2)
